Metadata-Version: 2.1
Name: dblpy-lib
Version: 0.1.3
Summary: A wrapper for dblp.org search api
Home-page: https://github.com/greenBene/dblpy
Author: Benedikt Maria Beckermann
Author-email: hello@benedikt.click
License: CC0 1.0 Universal
Platform: UNKNOWN
